collective.pwexpiry-1.0.0-py3.12-nspkg.pth
collective/pwexpiry/__init__.py
collective/pwexpiry/config.py
collective/pwexpiry/configure.zcml
collective/pwexpiry/events.py
collective/pwexpiry/example_validator.py
collective/pwexpiry/interfaces.py
collective/pwexpiry/logger.py
collective/pwexpiry/overrides.zcml
collective/pwexpiry/password_history_validator.py
collective/pwexpiry/patches.py
collective/pwexpiry/pwdisable_plugin.py
collective/pwexpiry/pwexpiry_plugin.py
collective/pwexpiry/setuphandlers.py
collective/pwexpiry/subscriber.py
collective/pwexpiry/testing.py
collective/pwexpiry/userdata.py
collective/pwexpiry/userdataschema.py
collective/pwexpiry/utils.py
collective/pwexpiry/actions/__init__.py
collective/pwexpiry/actions/actions.py
collective/pwexpiry/actions/configure.zcml
collective/pwexpiry/browser/__init__.py
collective/pwexpiry/browser/configure.zcml
collective/pwexpiry/browser/login.py
collective/pwexpiry/browser/emails/__init__.py
collective/pwexpiry/browser/emails/configure.zcml
collective/pwexpiry/browser/emails/emails.py
collective/pwexpiry/browser/js/fix_login_popup.js
collective/pwexpiry/browser/preferences/__init__.py
collective/pwexpiry/browser/preferences/configure.zcml
collective/pwexpiry/browser/preferences/pwexpirycontrolpanel.pt
collective/pwexpiry/browser/preferences/pwexpirycontrolpanel.py
collective/pwexpiry/browser/templates/login.pt
collective/pwexpiry/browser/templates/login_failsafe.pt
collective/pwexpiry/locales/collective.pwexpiry.pot
collective/pwexpiry/locales/manual.pot
collective/pwexpiry/locales/plone.pot
collective/pwexpiry/locales/update_locales.sh
collective/pwexpiry/locales/de/LC_MESSAGES/collective.pwexpiry.po
collective/pwexpiry/locales/de/LC_MESSAGES/plone.po
collective/pwexpiry/locales/en/LC_MESSAGES/collective.pwexpiry.po
collective/pwexpiry/locales/en/LC_MESSAGES/plone.po
collective/pwexpiry/locales/es/LC_MESSAGES/collective.pwexpiry.po
collective/pwexpiry/locales/es/LC_MESSAGES/plone.po
collective_pwexpiry-1.0.0.dist-info/METADATA
collective_pwexpiry-1.0.0.dist-info/WHEEL
collective_pwexpiry-1.0.0.dist-info/entry_points.txt
collective_pwexpiry-1.0.0.dist-info/namespace_packages.txt
collective_pwexpiry-1.0.0.dist-info/top_level.txt
collective_pwexpiry-1.0.0.dist-info/RECORD
