Metadata-Version: 2.4
Name: collective.pwexpiry
Version: 1.0.0
Summary: Emulate Active Directory password complexity requirements                   in Plone
Home-page: http://www.enfoldsystems.com
Author: Enfold Systems, Inc.
Author-email: info@enfoldsystems.com
License: ZPL
Classifier: Programming Language :: Python
Classifier: Programming Language :: Python :: 3.9
Classifier: Programming Language :: Python :: 3.10
Classifier: Programming Language :: Python :: 3.11
Classifier: Programming Language :: Python :: 3.12
Classifier: Topic :: Software Development :: Libraries :: Python Modules
Classifier: Topic :: Security
Classifier: Framework :: Plone
Classifier: Framework :: Plone :: 5.2
Classifier: Framework :: Plone :: 6.0
Classifier: License :: OSI Approved :: Zope Public License
Requires-Dist: setuptools
Requires-Dist: plone.api
Requires-Dist: collective.monkeypatcher
Provides-Extra: test
Requires-Dist: cssselect; extra == "test"
Requires-Dist: lxml; extra == "test"
Requires-Dist: mock; extra == "test"
Requires-Dist: plone.api>=1.8.5; extra == "test"
Requires-Dist: plone.app.robotframework; extra == "test"
Requires-Dist: plone.app.testing[robot]; extra == "test"
Requires-Dist: plone.browserlayer; extra == "test"
Requires-Dist: plone.cachepurging; extra == "test"
Requires-Dist: plone.testing; extra == "test"
Requires-Dist: robotsuite; extra == "test"
Requires-Dist: testfixtures; extra == "test"
Requires-Dist: transaction; extra == "test"
Requires-Dist: tzlocal; extra == "test"
Dynamic: author
Dynamic: author-email
Dynamic: classifier
Dynamic: description
Dynamic: home-page
Dynamic: keywords
Dynamic: license
Dynamic: provides-extra
Dynamic: requires-dist
Dynamic: summary
